beakerx_tabledisplay/__init__.py
beakerx_tabledisplay/_version.py
beakerx_tabledisplay/commands.py
beakerx_tabledisplay/install.py
beakerx_tabledisplay/table_display_runtim.py
beakerx_tabledisplay/tabledisplay.py
beakerx_tabledisplay/tableitems.py
beakerx_tabledisplay/labextension/package.json
beakerx_tabledisplay/labextension/static/00fd6016cebc419cac71.ttf
beakerx_tabledisplay/labextension/static/0152f420481d302f4de3.woff
beakerx_tabledisplay/labextension/static/06ef074ba5e7dc66c5d6.woff2
beakerx_tabledisplay/labextension/static/08c8229182fd845d3edb.woff
beakerx_tabledisplay/labextension/static/133.8239e41747a980c81691.js
beakerx_tabledisplay/labextension/static/1568ca1aa82f7b3749df.ttf
beakerx_tabledisplay/labextension/static/16a5bb85a7418b0e5935.woff2
beakerx_tabledisplay/labextension/static/180a9e8c89d5b4cb8a2e.ttf
beakerx_tabledisplay/labextension/static/1abcf0714d431568bc7d.woff2
beakerx_tabledisplay/labextension/static/1ffe0db6dbffbd0460ca.ttf
beakerx_tabledisplay/labextension/static/215.79e4c0e4cab686c4393b.js
beakerx_tabledisplay/labextension/static/216cd1b1aa23fe169e41.ttf
beakerx_tabledisplay/labextension/static/23225cffdca86a65f1d0.woff2
beakerx_tabledisplay/labextension/static/27df6e52f4329466744e.woff2
beakerx_tabledisplay/labextension/static/2a956ec96f93519a122e.woff
beakerx_tabledisplay/labextension/static/301943e01b59a2e5844d.woff
beakerx_tabledisplay/labextension/static/400.dfa0314ece48a2392097.js
beakerx_tabledisplay/labextension/static/400.dfa0314ece48a2392097.js.LICENSE.txt
beakerx_tabledisplay/labextension/static/410f03b5cca26e017d80.woff2
beakerx_tabledisplay/labextension/static/41b2ef81df7103de00d4.woff
beakerx_tabledisplay/labextension/static/44c04e130b4333b24380.woff2
beakerx_tabledisplay/labextension/static/46799c96df52b710ce84.ttf
beakerx_tabledisplay/labextension/static/527.e0a49eb59da3aef9dea6.js
beakerx_tabledisplay/labextension/static/58.6fe515f86f3a728e5b04.js
beakerx_tabledisplay/labextension/static/581b07f16ac528a7d6e6.woff
beakerx_tabledisplay-2.4.4.dist-info/LICENSE
beakerx_tabledisplay-2.4.4.dist-info/METADATA
beakerx_tabledisplay-2.4.4.dist-info/WHEEL
beakerx_tabledisplay-2.4.4.dist-info/entry_points.txt
beakerx_tabledisplay-2.4.4.dist-info/top_level.txt
beakerx_tabledisplay-2.4.4.dist-info/RECORD
