Metadata-Version: 2.1
Name: beakerx_tabledisplay
Version: 2.4.4
Summary: BeakerX: Beaker TableDisplay Extension for Jupyter Notebook and Lab
Home-page: http://beakerx.com/
Author: Two Sigma Open Source, LLC
Author-email: beakerx-feedback@twosigma.com
License: Apache-2.0
Keywords: ipython,jupyter,widgets
Platform: Linux
Platform: Mac OS X
Platform: Windows
Classifier: License :: OSI Approved :: Apache Software License
Classifier: Development Status :: 5 - Production/Stable
Classifier: Framework :: IPython
Classifier: Intended Audience :: Developers
Classifier: Intended Audience :: Science/Research
Classifier: Topic :: Multimedia :: Graphics
Classifier: Programming Language :: Python :: 3
Classifier: Programming Language :: Python :: 3.6
Classifier: Programming Language :: Python :: 3.7
Classifier: Programming Language :: Python :: 3.8
Classifier: Programming Language :: Python :: 3.9
Classifier: Programming Language :: Python :: 3.10
Classifier: Framework :: Jupyter
Requires-Python: >=3
License-File: LICENSE
Requires-Dist: beakerx-base <3,>=2.3
Requires-Dist: numpy
Requires-Dist: pandas
